tapdata_cli/__init__.py
tapdata_cli/check.py
tapdata_cli/cli.py
tapdata_cli/config_parse.py
tapdata_cli/default.ini
tapdata_cli/graph.py
tapdata_cli/history.sqlite
tapdata_cli/ipython_config.py
tapdata_cli/log.py
tapdata_cli/params/__init__.py
tapdata_cli/params/datasource.py
tapdata_cli/params/job.py
tapdata_cli/request.py
tapdata_cli/startup/README
tapdata_cli-2.3.2.dist-info/WHEEL
tapdata_cli-2.3.2.dist-info/METADATA
tapdata_cli-2.3.2.dist-info/RECORD
