Metadata-Version: 2.1
Name: tapdata-cli
Version: 2.3.2
Summary: Tapdata Python Sdk
Home-page: https://github.com/tapdata/tapdata/tree/master/tapshell
License: Apache V2
Author: Tapdata
Author-email: team@tapdata.io
Requires-Python: >=3.7,<4.0
Classifier: License :: Other/Proprietary License
Classifier: Programming Language :: Python :: 3
Classifier: Programming Language :: Python :: 3.7
Classifier: Programming Language :: Python :: 3.8
Classifier: Programming Language :: Python :: 3.9
Classifier: Programming Language :: Python :: 3.10
Requires-Dist: PyYAML (==5.4.1)
Requires-Dist: allure-pytest (>=2.9.45,<3.0.0)
Requires-Dist: asyncio (==3.4.3)
Requires-Dist: atomicwrites (==1.4.0)
Requires-Dist: attrs (==21.2.0)
Requires-Dist: certifi (==2020.12.5)
Requires-Dist: chardet (==4.0.0)
Requires-Dist: colorama (==0.4.4)
Requires-Dist: colorlog (==5.0.1)
Requires-Dist: idna (==2.10)
Requires-Dist: iniconfig (==1.1.1)
Requires-Dist: javascripthon (>=0.12,<0.13)
Requires-Dist: jupyter (>=1.0.0,<2.0.0)
Requires-Dist: packaging (==20.9)
Requires-Dist: pluggy (==0.13.1)
Requires-Dist: py (==1.10.0)
Requires-Dist: pymongo (==4.1.1)
Requires-Dist: pyparsing (==2.4.7)
Requires-Dist: pytest (>=7.1.2,<8.0.0)
Requires-Dist: pytest-parallel (>=0.1.1,<0.2.0)
Requires-Dist: requests (==2.25.1)
Requires-Dist: toml (==0.10.2)
Requires-Dist: urllib3 (==1.26.4)
Requires-Dist: websockets (==10)
Project-URL: Repository, https://github.com/tapdata/tapdata/tree/master/tapshell
